AUTHORS.rst
CONTRIBUTING.rst
HISTORY.rst
LICENSE
MANIFEST.in
README.rst
setup.cfg
setup.py
docs/Makefile
docs/authors.rst
docs/conf.py
docs/contributing.rst
docs/history.rst
docs/index.rst
docs/installation.rst
docs/make.bat
docs/readme.rst
docs/usage.rst
htmltopdf/__init__.py
htmltopdf/wkhtmltopdf.py
htmltopdf.egg-info/PKG-INFO
htmltopdf.egg-info/SOURCES.txt
htmltopdf.egg-info/dependency_links.txt
htmltopdf.egg-info/not-zip-safe
htmltopdf.egg-info/top_level.txt
tests/__init__.py
tests/test_htmltopdf.py