Metadata-Version: 1.1
Name: htmltopdf
Version: 0.1.1
Summary: Convert HTML to PDF.
Home-page: https://github.com/takis/htmltopdf
Author: Panagiotis H.M. Issaris
Author-email: takis@issaris.org
License: ISCL
Keywords: htmltopdf
Platform: UNKNOWN
Classifier: Development Status :: 2 - Pre-Alpha
Classifier: Intended Audience :: Developers
Classifier: License :: OSI Approved :: ISC License (ISCL)
Classifier: Natural Language :: English
Classifier: Programming Language :: Python :: 2
Classifier: Programming Language :: Python :: 2.6
Classifier: Programming Language :: Python :: 2.7
Classifier: Programming Language :: Python :: 3
Classifier: Programming Language :: Python :: 3.3
Classifier: Programming Language :: Python :: 3.4
